langx/__init__.py
langx/x.py
langx/compiler/__init__.py
langx/compiler/compiler.py
langx/decompiler/__init__.py
langx/decompiler/c/__init__.py
langx/decompiler/c/decompile.py
langx/decompiler/cpp/__init__.py
langx/decompiler/cpp/decompile.py
langx/decompiler/java/__init__.py
langx/decompiler/java/decompile.py
langx/decompiler/python/__init__.py
langx/decompiler/python/decompile.py
langx/opcode/__init__.py
langx/opcode/op_type.py
langx/opcode/opcode.py
langx/parser/__init__.py
langx/parser/parser.py
langx/parser/node/__init__.py
langx/parser/node/binary_operator_node.py
langx/parser/node/expr_node.py
langx/parser/node/number_node.py
langx/parser/node/print_node.py
langx/parser/node/program_node.py
langx/parser/node/string_node.py
langx/tokenizer/__init__.py
langx/tokenizer/tokenizer.py
langx/utils/__init__.py
langx/utils/error.py
langx/utils/tree_walker.py
langx/vm/__init__.py
langx/vm/vm.py
langx/webdebug/__init__.py
langx/webdebug/app.py
langx/webdebug/run_app.py
x/__init__.py
x/x.py
x/compiler/__init__.py
x/compiler/compiler.py
x/decompiler/__init__.py
x/decompiler/c/__init__.py
x/decompiler/c/decompile.py
x/decompiler/cpp/__init__.py
x/decompiler/cpp/decompile.py
x/decompiler/java/__init__.py
x/decompiler/java/decompile.py
x/decompiler/python/__init__.py
x/decompiler/python/decompile.py
x/opcode/__init__.py
x/opcode/op_type.py
x/opcode/opcode.py
x/parser/__init__.py
x/parser/parser.py
x/parser/node/__init__.py
x/parser/node/binary_operator_node.py
x/parser/node/expr_node.py
x/parser/node/number_node.py
x/parser/node/print_node.py
x/parser/node/program_node.py
x/parser/node/string_node.py
x/tokenizer/__init__.py
x/tokenizer/tokenizer.py
x/utils/__init__.py
x/utils/error.py
x/utils/tree_walker.py
x/vm/__init__.py
x/vm/vm.py
x/webdebug/__init__.py
x/webdebug/app.py
x/webdebug/run_app.py
langx-0.1a0.dist-info/METADATA
langx-0.1a0.dist-info/WHEEL
langx-0.1a0.dist-info/entry_points.txt
langx-0.1a0.dist-info/top_level.txt
langx-0.1a0.dist-info/RECORD
