Metadata-Version: 2.1
Name: langx
Version: 0.1a0
Summary: A placeholder language with shareable bytecode IR
Home-page: https://github.com/frankhart2018/X
Author: Siddhartha Dhar Choudhury
Author-email: sdharchou@gmail.com
License: MIT
Platform: UNKNOWN
Classifier: License :: OSI Approved :: MIT License
Classifier: Programming Language :: Python :: 3
Classifier: Programming Language :: Python :: 3.10
Classifier: Programming Language :: Python :: 3.9
Classifier: Programming Language :: Python :: 3.8
Classifier: Programming Language :: Python :: 3.7
Classifier: Programming Language :: Python :: 3.6
Requires-Dist: flask
